geodesicpandas/__init__.py
geodesicpandas/_compat.py
geodesicpandas/_config.py
geodesicpandas/_decorator.py
geodesicpandas/_version.py
geodesicpandas/accessors.py
geodesicpandas/array.py
geodesicpandas/base.py
geodesicpandas/conftest.py
geodesicpandas/explore.py
geodesicpandas/geodataframe.py
geodesicpandas/geoseries.py
geodesicpandas/plotting.py
geodesicpandas/sindex.py
geodesicpandas/testing.py
geodesicpandas/datasets/__init__.py
geodesicpandas/io/__init__.py
geodesicpandas/io/_geoarrow.py
geodesicpandas/io/_pyarrow_hotfix.py
geodesicpandas/io/arrow.py
geodesicpandas/io/file.py
geodesicpandas/io/sql.py
geodesicpandas/io/util.py
geodesicpandas/io/tests/__init__.py
geodesicpandas/io/tests/generate_legacy_storage_files.py
geodesicpandas/io/tests/test_arrow.py
geodesicpandas/io/tests/test_file.py
geodesicpandas/io/tests/test_file_geom_types_drivers.py
geodesicpandas/io/tests/test_geoarrow.py
geodesicpandas/io/tests/test_infer_schema.py
geodesicpandas/io/tests/test_pickle.py
geodesicpandas/io/tests/test_sql.py
geodesicpandas/tests/__init__.py
geodesicpandas/tests/test_api.py
geodesicpandas/tests/test_array.py
geodesicpandas/tests/test_compat.py
geodesicpandas/tests/test_config.py
geodesicpandas/tests/test_crs.py
geodesicpandas/tests/test_datasets.py
geodesicpandas/tests/test_decorator.py
geodesicpandas/tests/test_dissolve.py
geodesicpandas/tests/test_explore.py
geodesicpandas/tests/test_extension_array.py
geodesicpandas/tests/test_geocode.py
geodesicpandas/tests/test_geodataframe.py
geodesicpandas/tests/test_geom_methods.py
geodesicpandas/tests/test_geoseries.py
geodesicpandas/tests/test_merge.py
geodesicpandas/tests/test_op_output_types.py
geodesicpandas/tests/test_overlay.py
geodesicpandas/tests/test_pandas_accessor.py
geodesicpandas/tests/test_pandas_methods.py
geodesicpandas/tests/test_plotting.py
geodesicpandas/tests/test_show_versions.py
geodesicpandas/tests/test_sindex.py
geodesicpandas/tests/test_testing.py
geodesicpandas/tests/test_types.py
geodesicpandas-0.1.3.dist-info/LICENSE 2.txt
geodesicpandas-0.1.3.dist-info/LICENSE.txt
geodesicpandas-0.1.3.dist-info/METADATA
geodesicpandas-0.1.3.dist-info/WHEEL
geodesicpandas-0.1.3.dist-info/top_level.txt
geodesicpandas-0.1.3.dist-info/RECORD
