Metadata-Version: 2.2
Name: geodesicpandas
Version: 0.1.3
Summary: Fork of GeoPandas with additional geodesic capabilities
Author-email: Kelsey Jordahl <kjordahl@alum.mit.edu>
Maintainer: GeoPandas contributors
License: BSD 3-Clause
Project-URL: Repository, https://github.com/andersonstolfi/geopandas
Keywords: GIS,cartography,pandas,shapely
Classifier: Development Status :: 5 - Production/Stable
Classifier: Intended Audience :: Science/Research
Classifier: License :: OSI Approved :: BSD License
Classifier: Operating System :: OS Independent
Classifier: Programming Language :: Python :: 3
Classifier: Programming Language :: Python :: 3 :: Only
Classifier: Topic :: Scientific/Engineering :: GIS
Requires-Python: >=3.10
License-File: LICENSE 2.txt
License-File: LICENSE.txt
Requires-Dist: geopandas>=0.14.0
Requires-Dist: geographiclib>=2.0
Provides-Extra: all
Requires-Dist: psycopg[binary]>=3.1.0; extra == "all"
Requires-Dist: SQLAlchemy>=2.0; extra == "all"
Requires-Dist: geopy; extra == "all"
Requires-Dist: matplotlib>=3.7; extra == "all"
Requires-Dist: mapclassify>=2.5; extra == "all"
Requires-Dist: xyzservices; extra == "all"
Requires-Dist: folium; extra == "all"
Requires-Dist: GeoAlchemy2; extra == "all"
Requires-Dist: pyarrow>=10.0.0; extra == "all"
Requires-Dist: scipy; extra == "all"
Provides-Extra: dev
Requires-Dist: pytest>=3.1.0; extra == "dev"
Requires-Dist: pytest-cov; extra == "dev"
Requires-Dist: pytest-xdist; extra == "dev"
Requires-Dist: codecov; extra == "dev"
Requires-Dist: pre-commit; extra == "dev"
Requires-Dist: ruff; extra == "dev"
